swissfit/__init__.py
swissfit/fit.py
swissfit/empirical_bayes/__init__.py
swissfit/empirical_bayes/empirical_bayes.py
swissfit/empirical_bayes/single_parameter_surrogate.py
swissfit/interpolators/__init__.py
swissfit/interpolators/bspline.py
swissfit/interpolators/interpolator.py
swissfit/machine_learning/__init__.py
swissfit/machine_learning/feedforward.py
swissfit/machine_learning/kolmogrov_arnold.py
swissfit/machine_learning/neuralnetwork.py
swissfit/machine_learning/radial_basis.py
swissfit/model_averaging/__init__.py
swissfit/model_averaging/model_averaging.py
swissfit/monte_carlo/__init__.py
swissfit/monte_carlo/montecarlo.py
swissfit/monte_carlo/vegas.py
swissfit/numerical_tools/__init__.py
swissfit/numerical_tools/linalg.py
swissfit/optimizers/__init__.py
swissfit/optimizers/optimizer.py
swissfit/optimizers/scipy_basin_hopping.py
swissfit/optimizers/scipy_least_squares.py
swissfit/optimizers/scipy_minimize.py
swissfit/other_tools/__init__.py
swissfit/other_tools/progress.py
swissfit-0.23.dist-info/LICENSE
swissfit-0.23.dist-info/METADATA
swissfit-0.23.dist-info/WHEEL
swissfit-0.23.dist-info/top_level.txt
swissfit-0.23.dist-info/RECORD
